fast_body_tracker/__init__.py
fast_body_tracker/initializer.py
fast_body_tracker/k4a/__init__.py
fast_body_tracker/k4a/_k4a.py
fast_body_tracker/k4a/_k4a_types.py
fast_body_tracker/k4a/calibration.py
fast_body_tracker/k4a/capture.py
fast_body_tracker/k4a/configuration.py
fast_body_tracker/k4a/device.py
fast_body_tracker/k4a/image.py
fast_body_tracker/k4a/imu_sample.py
fast_body_tracker/k4a/k4a_const.py
fast_body_tracker/k4a/transformation.py
fast_body_tracker/k4abt/__init__.py
fast_body_tracker/k4abt/_k4abt.py
fast_body_tracker/k4abt/_k4abt_types.py
fast_body_tracker/k4abt/body.py
fast_body_tracker/k4abt/frame.py
fast_body_tracker/k4abt/kabt_const.py
fast_body_tracker/k4abt/tracker.py
fast_body_tracker/k4abt/tracker_configuration.py
fast_body_tracker/k4arecord/__init__.py
fast_body_tracker/k4arecord/_k4arecord.py
fast_body_tracker/k4arecord/_k4arecordTypes.py
fast_body_tracker/k4arecord/datablock.py
fast_body_tracker/k4arecord/playback.py
fast_body_tracker/k4arecord/record.py
fast_body_tracker/k4arecord/record_configuration.py
fast_body_tracker/utils/__init__.py
fast_body_tracker/utils/keyboard_closer.py
fast_body_tracker/utils/performace_calculator.py
fast_body_tracker/utils/visualizer.py
fast_body_tracker-0.1.0.dist-info/METADATA
fast_body_tracker-0.1.0.dist-info/WHEEL
fast_body_tracker-0.1.0.dist-info/licenses/LICENSE
fast_body_tracker-0.1.0.dist-info/RECORD
