Metadata-Version: 2.4
Name: fast_body_tracker
Version: 0.1.0
Summary: Fast depth camera body tracker
Author: Ibai Gorordo, Elia Balugani
License-Expression: MIT
License-File: LICENSE
Classifier: License :: OSI Approved :: MIT License
Classifier: Operating System :: Microsoft :: Windows
Classifier: Operating System :: POSIX :: Linux
Classifier: Programming Language :: Python :: 3
Classifier: Topic :: Scientific/Engineering :: Human Machine Interfaces
Classifier: Topic :: Scientific/Engineering :: Image Recognition
Classifier: Topic :: Scientific/Engineering :: Visualization
Requires-Python: >=3.10
Requires-Dist: matplotlib>=3.10.8
Requires-Dist: numpy>=1.22.2
Requires-Dist: opencv-python>=4.5.5
Requires-Dist: pynput>=1.8.1
Requires-Dist: pyside6>=6.10.0
Requires-Dist: vispy>=0.15.2
